pyerepfit/__init__.py
pyerepfit/erepfit.py
pyerepfit/erepfit_input_schema.json
pyerepfit/evaluator.py
pyerepfit/inputdata.py
pyerepfit/rep_basis.py
pyerepfit/rep_model.py
pyerepfit/rep_spline.py
pyerepfit/utils.py
pyerepfit-0.1.data/scripts/erepfit
pyerepfit-0.1.dist-info/METADATA
pyerepfit-0.1.dist-info/RECORD
pyerepfit-0.1.dist-info/WHEEL
pyerepfit-0.1.dist-info/top_level.txt
