Metadata-Version: 2.1
Name: pyerepfit
Version: 0.1
Summary: The python verion of the DFTB repulsive potential fitting tool, erepfit.
Home-page: https://bitbucket.org/solccp/pyerepfit.git
Author: Chien-Pin Chou
Author-email: sol.chou@gmail.com
License: GPLv3
Platform: UNKNOWN
Classifier: Programming Language :: Python :: 3.6
Classifier: Development Status :: 4 - Beta
Classifier: Environment :: Console
Classifier: License :: OSI Approved :: GNU General Public License v3 (GPLv3)
Classifier: Operating System :: OS Independent
Classifier: Topic :: Scientific/Engineering :: Chemistry
